granola_client/__init__.py
granola_client/client.py
granola_client/errors.py
granola_client/http_client.py
granola_client/pagination.py
granola_client/types.py
granola_client/utils.py
granola_client-0.3.0.dist-info/METADATA
granola_client-0.3.0.dist-info/WHEEL
granola_client-0.3.0.dist-info/licenses/LICENSE
granola_client-0.3.0.dist-info/RECORD
