Metadata-Version: 2.4
Name: granola-client
Version: 0.3.0
Summary: A Python client for the Granola API
Project-URL: Homepage, https://github.com/anjor/granola-py-client
Project-URL: Repository, https://github.com/anjor/granola-py-client
Author: Anjor Kanekar
License: MIT
License-File: LICENSE
Classifier: Intended Audience :: Developers
Classifier: License :: OSI Approved :: MIT License
Classifier: Operating System :: OS Independent
Classifier: Programming Language :: Python :: 3.13
Classifier: Topic :: Software Development :: Libraries :: Python Modules
Requires-Python: >=3.13
Requires-Dist: httpx<0.28.0,>=0.25.0
Requires-Dist: pydantic<3.0,>=2.0
Requires-Dist: python-dotenv>=1.1.0
Provides-Extra: dev
Requires-Dist: black>=23.0.0; extra == 'dev'
Requires-Dist: isort>=5.0.0; extra == 'dev'
Requires-Dist: pytest-asyncio>=0.20.0; extra == 'dev'
Requires-Dist: pytest-httpx>=0.20.0; extra == 'dev'
Requires-Dist: pytest>=7.0.0; extra == 'dev'
Requires-Dist: ruff>=0.1.0; extra == 'dev'
